django_view_tracking/__init__.py
django_view_tracking/admin.py
django_view_tracking/apps.py
django_view_tracking/cleanup.py
django_view_tracking/middleware.py
django_view_tracking/models.py
django_view_tracking/migrations/0001_initial.py
django_view_tracking/migrations/__init__.py
django_view_tracking-0.2.dist-info/LICENSE
django_view_tracking-0.2.dist-info/METADATA
django_view_tracking-0.2.dist-info/WHEEL
django_view_tracking-0.2.dist-info/top_level.txt
django_view_tracking-0.2.dist-info/RECORD
