Metadata-Version: 2.1
Name: django-view-tracking
Version: 0.2
Summary: Simple logging of user access to URLs in Django.
Home-page: https://gitlab.com/accu-trade/django-view-tracking
Author: Accu-Trade LLC
License: MIT
Platform: UNKNOWN
Classifier: Environment :: Web Environment
Classifier: Framework :: Django
Classifier: Intended Audience :: Developers
Classifier: License :: OSI Approved :: MIT License
Classifier: Operating System :: OS Independent
Classifier: Programming Language :: Python :: 3
Requires-Python: >=3.6
License-File: LICENSE
Requires-Dist: Django >=2.2
